opticedge_types/__init__.py
opticedge_types/constants/__init__.py
opticedge_types/constants/card.py
opticedge_types/enums/__init__.py
opticedge_types/enums/card.py
opticedge_types/enums/user.py
opticedge_types-1.0.18.dist-info/METADATA
opticedge_types-1.0.18.dist-info/WHEEL
opticedge_types-1.0.18.dist-info/top_level.txt
opticedge_types-1.0.18.dist-info/RECORD
