Metadata-Version: 2.4
Name: opticedge_types
Version: 1.0.18
Summary: Common types for opticedge
Author-email: velopace <velopace7@gmail.com>
License: MIT
Provides-Extra: dev
